{
 "actions": [],
 "allow_rename": 1,
 "creation": "2026-03-06 11:28:38.553954",
 "doctype": "DocType",
 "editable_grid": 1,
 "engine": "InnoDB",
 "field_order": [
  "employee",
  "observation",
  "quantity"
 ],
 "fields": [
  {
   "fieldname": "employee",
   "fieldtype": "Link",
   "in_list_view": 1,
   "label": "Employee",
   "options": "Employee"
  },
  {
   "fieldname": "observation",
   "fieldtype": "Data",
   "in_list_view": 1,
   "label": "Observation"
  },
  {
   "fieldname": "quantity",
   "fieldtype": "Float",
   "in_list_view": 1,
   "label": "Quantity"
  }
 ],
 "grid_page_length": 50,
 "index_web_pages_for_search": 1,
 "istable": 1,
 "links": [],
 "modified": "2026-03-06 13:53:10.009012",
 "modified_by": "Administrator",
 "module": "Winery",
 "name": "Batch Operation Details",
 "owner": "Administrator",
 "permissions": [],
 "row_format": "Dynamic",
 "rows_threshold_for_grid_search": 20,
 "sort_field": "modified",
 "sort_order": "DESC",
 "states": []
}